ladybug_rhino/__init__.py
ladybug_rhino/__main__.py
ladybug_rhino/bakedisplay.py
ladybug_rhino/bakegeometry.py
ladybug_rhino/bakeobjects.py
ladybug_rhino/color.py
ladybug_rhino/colorize.py
ladybug_rhino/command.py
ladybug_rhino/config.py
ladybug_rhino/download.py
ladybug_rhino/fromgeometry.py
ladybug_rhino/fromhoneybee.py
ladybug_rhino/fromobjects.py
ladybug_rhino/ghpath.py
ladybug_rhino/grasshopper.py
ladybug_rhino/intersect.py
ladybug_rhino/light.py
ladybug_rhino/openstudio.py
ladybug_rhino/planarize.py
ladybug_rhino/preview.py
ladybug_rhino/pythonpath.py
ladybug_rhino/resourcepath.py
ladybug_rhino/text.py
ladybug_rhino/togeometry.py
ladybug_rhino/viewport.py
ladybug_rhino/visset.py
ladybug_rhino/cli/__init__.py
ladybug_rhino/versioning/__init__.py
ladybug_rhino/versioning/change.py
ladybug_rhino/versioning/component.py
ladybug_rhino/versioning/diff.py
ladybug_rhino/versioning/export.py
ladybug_rhino/versioning/gather.py
ladybug_rhino/versioning/legacy.py
ladybug_rhino/versioning/release.py
ladybug_rhino/versioning/userobject.py
ladybug_rhino-1.43.16.dist-info/licenses/LICENSE
ladybug_rhino-1.43.16.dist-info/METADATA
ladybug_rhino-1.43.16.dist-info/WHEEL
ladybug_rhino-1.43.16.dist-info/entry_points.txt
ladybug_rhino-1.43.16.dist-info/top_level.txt
ladybug_rhino-1.43.16.dist-info/RECORD
