Metadata-Version: 2.4
Name: ladybug-rhino
Version: 1.43.16
Summary: A library for communicating between Ladybug Tools core libraries and Rhinoceros CAD.
Home-page: https://github.com/ladybug-tools/ladybug-rhino
Author: Ladybug Tools
Author-email: info@ladybug.tools
License: AGPL-3.0
Classifier: Programming Language :: Python :: 2.7
Classifier: Programming Language :: Python :: Implementation :: IronPython
Classifier: Operating System :: OS Independent
License-File: LICENSE
Requires-Dist: ladybug-display>=0.5.0
Dynamic: author
Dynamic: author-email
Dynamic: classifier
Dynamic: description
Dynamic: description-content-type
Dynamic: home-page
Dynamic: license
Dynamic: license-file
Dynamic: requires-dist
Dynamic: summary
